ncmv3/__init__.py
ncmv3/ncmv3.py
ncmv3-0.0.3.dist-info/LICENSE
ncmv3-0.0.3.dist-info/METADATA
ncmv3-0.0.3.dist-info/WHEEL
ncmv3-0.0.3.dist-info/top_level.txt
ncmv3-0.0.3.dist-info/RECORD
