Metadata-Version: 2.1
Name: ncmv3
Version: 0.0.3
Summary: Python client library for Cradlepoint NCM APIv3
Home-page: https://github.com/nathanwiens/ncmv3
Author: Nathan Wiens - Cradlepoint
Author-email: nathan.wiens@cradlepoint.com
Requires-Python: >=3.6
License-File: LICENSE
Requires-Dist: requests
Requires-Dist: urllib3
